{
  "page": {
    "total": 378,
    "rows": [
      {
        "id": 112896,
        "industry": "186",
        "industryName": "科学研究和技术服务业",
        "industryitem": null,
        "industryitemName": null,
        "industrysubitem": "18600201",
        "industrysubitemName": null,
        "checkType": "方法与工艺",
        "inspectionType": "03",
        "checkTypeText": null,
        "point": "不达标的送检机动车，机动车安全技术检验机构未告知送检人整改，未在符合要求后再进行安全技术检验",
        "basis": "《机动车安全技术检验项目和方法》（GB 21861-2014）第5.1.2.1条",
        "standard": "送检机动车应清洁，无明显漏油、漏水、漏气现象，轮胎完好，轮胎气压正常且胎冠花纹中无异物，发动机应运转平稳，怠速稳定，无异响；装有车载诊断系统（OBD）的车辆，不应有与防抱死制动系统（ABS）、电动助力转向系统（EPS）及其他与行车安全相关的故障信息对达不到以上基本要求的送检机动车，机动车安全技术检验机构应告知送检人整改，符合要求后再进行安全技术检验",
        "level": "01",
        "levelText": null,
        "dangerBasis": "",
        "isvalid": null,
        "createBy": null,
        "createDate": null,
        "updateBy": null,
        "updateDate": null
      },
      {
        "id": 62464,
        "industry": "186",
        "industryName": "科学研究和技术服务业",
        "industryitem": "186002",
        "industryitemName": null,
        "industrysubitem": "18600201",
        "industrysubitemName": null,
        "checkType": "技术要求",
        "inspectionType": "01",
        "checkTypeText": null,
        "point": "机动车未使用机动车号牌专用固封装置固定号牌，固封装置应齐全、安装牢固",
        "basis": "《机动车安全技术检验项目和方法》（GB 21861-2014）第6.4.5.2条",
        "standard": "号牌及号牌安装应满足以下要求：B）机动车应使用机动车号牌专用固封装置固定号牌，固封装置应齐全、安装牢固",
        "level": "01",
        "levelText": null,
        "dangerBasis": "",
        "isvalid": null,
        "createBy": null,
        "createDate": null,
        "updateBy": null,
        "updateDate": null
      },
      {
        "id": 112897,
        "industry": "186",
        "industryName": "科学研究和技术服务业",
        "industryitem": null,
        "industryitemName": null,
        "industrysubitem": "18600201",
        "industrysubitemName": null,
        "checkType": "方法与工艺",
        "inspectionType": "03",
        "checkTypeText": null,
        "point": "在用机动车检验时，未提供送检机动车的机动车行驶证或有效的机动车交通事故责任强制保险凭证",
        "basis": "《机动车安全技术检验项目和方法》（GB 21861-2014）第5.1.2.2条",
        "standard": "在用机动车检验时，应提供送检机动车的机动车行驶证和有效的机动车交通事故责任强制保险凭证",
        "level": "01",
        "levelText": null,
        "dangerBasis": "",
        "isvalid": null,
        "createBy": null,
        "createDate": null,
        "updateBy": null,
        "updateDate": null
      },
      {
        "id": 62465,
        "industry": "186",
        "industryName": "科学研究和技术服务业",
        "industryitem": "186002",
        "industryitemName": null,
        "industrysubitem": "18600201",
        "industrysubitemName": null,
        "checkType": "技术要求",
        "inspectionType": "01",
        "checkTypeText": null,
        "point": "使用号牌架辅助安装时，号牌架内侧边缘距离机动车登记编号字符边缘应小于5MM，或使用可拆卸号牌架和可翻转号牌架",
        "basis": "《机动车安全技术检验项目和方法》（GB 21861-2014）第6.4.5.2条",
        "standard": "号牌及号牌安装应满足以下要求：C）使用号牌架辅助安装时，号牌架内侧边缘距离机动车登记编号字符边缘应大于5MM，不应使用可拆卸号牌架和可翻转号牌架",
        "level": "01",
        "levelText": null,
        "dangerBasis": "",
        "isvalid": null,
        "createBy": null,
        "createDate": null,
        "updateBy": null,
        "updateDate": null
      },
      {
        "id": 112898,
        "industry": "186",
        "industryName": "科学研究和技术服务业",
        "industryitem": null,
        "industryitemName": null,
        "industrysubitem": "18600201",
        "industrysubitemName": null,
        "checkType": "方法与工艺",
        "inspectionType": "03",
        "checkTypeText": null,
        "point": "注册登记检验时，送检机动车的车辆品牌/型号与机动车出厂合格证（对进口车为海关货物进口证明书）不一致",
        "basis": "《机动车安全技术检验项目和方法》（GB 21861-2014）第6.1.1.1条",
        "standard": "注册登记检验时，送检机动车的车辆品牌/型号应与机动车出厂合格证（对进口车为海关货物进口证明书）一致",
        "level": "01",
        "levelText": null,
        "dangerBasis": "",
        "isvalid": null,
        "createBy": null,
        "createDate": null,
        "updateBy": null,
        "updateDate": null
      },
      {
        "id": 62466,
        "industry": "186",
        "industryName": "科学研究和技术服务业",
        "industryitem": "186002",
        "industryitemName": null,
        "industrysubitem": "18600201",
        "industrysubitemName": null,
        "checkType": "技术要求",
        "inspectionType": "01",
        "checkTypeText": null,
        "point": "号牌及号牌安装不满足以下要求：不应出现影响号牌正常视认的加装、改装等情形",
        "basis": "《机动车安全技术检验项目和方法》（GB 21861-2014）第6.4.5.2条",
        "standard": "号牌及号牌安装应满足以下要求：D）不应出现影响号牌正常视认的加装、改装等情形",
        "level": "01",
        "levelText": null,
        "dangerBasis": "",
        "isvalid": null,
        "createBy": null,
        "createDate": null,
        "updateBy": null,
        "updateDate": null
      },
      {
        "id": 112899,
        "industry": "186",
        "industryName": "科学研究和技术服务业",
        "industryitem": null,
        "industryitemName": null,
        "industrysubitem": "18600201",
        "industrysubitemName": null,
        "checkType": "方法与工艺",
        "inspectionType": "03",
        "checkTypeText": null,
        "point": "在用机动车检验时，送检机动车的号牌号码/车辆类型、车辆品牌/型号，与机动车行驶证签注的内容不一致",
        "basis": "《机动车安全技术检验项目和方法》（GB 21861-2014）第6.1.1.2条",
        "standard": "在用机动车检验时，送检机动车的号牌号码/车辆类型、车辆品牌/型号，应与机动车行驶证签注的内容一致",
        "level": "01",
        "levelText": null,
        "dangerBasis": "",
        "isvalid": null,
        "createBy": null,
        "createDate": null,
        "updateBy": null,
        "updateDate": null
      },
      {
        "id": 62467,
        "industry": "186",
        "industryName": "科学研究和技术服务业",
        "industryitem": "186002",
        "industryitemName": null,
        "industrysubitem": "18600201",
        "industrysubitemName": null,
        "checkType": "技术要求",
        "inspectionType": "01",
        "checkTypeText": null,
        "point": "车辆未设置能够满足号牌安装要求的前、后号牌板（架），摩托车未设置有能满足号牌安装要求的后号牌板（架）；前号牌板（架）应设于前面的左侧（按机动车前进方向），后号牌板（架）应设于后面的右侧",
        "basis": "《机动车安全技术检验项目和方法》（GB 21861-2014）第6.4.5.3条",
        "standard": "注册登记检验时，号牌及号牌安装还应满足：A）车辆应设置能够满足号牌安装要求的前、后号牌板（架），但摩托车只需设置有能满足号牌安装要求的后号牌板（架）；前号牌板（架）应设于前面的中部或右侧（按机动车前进方向），后号牌板（架）应设于后面的中部或左侧",
        "level": "01",
        "levelText": null,
        "dangerBasis": "",
        "isvalid": null,
        "createBy": null,
        "createDate": null,
        "updateBy": null,
        "updateDate": null
      },
      {
        "id": 112900,
        "industry": "186",
        "industryName": "科学研究和技术服务业",
        "industryitem": null,
        "industryitemName": null,
        "industrysubitem": "18600201",
        "industrysubitemName": null,
        "checkType": "方法与工艺",
        "inspectionType": "03",
        "checkTypeText": null,
        "point": "在用机动车检验时，送检机动车的车辆识别別代号（或整车出厂编号）与机动车行驶证签注的内容不一致，或出现被凿改、挖补、打磨，擅自重新打刻等现象",
        "basis": "《机动车安全技术检验项目和方法》（GB 21861-2014）第6.1.2.1条",
        "standard": "在用机动车检验时，送检机动车的车辆识别別代号（或整车出厂编号）应与机动车行驶证签注的内容一致，且不应出现被凿改、挖补、打磨，擅自重新打刻等现象",
        "level": "01",
        "levelText": null,
        "dangerBasis": "",
        "isvalid": null,
        "createBy": null,
        "createDate": null,
        "updateBy": null,
        "updateDate": null
      },
      {
        "id": 62468,
        "industry": "186",
        "industryName": "科学研究和技术服务业",
        "industryitem": "186002",
        "industryitemName": null,
        "industrysubitem": "18600201",
        "industrysubitemName": null,
        "checkType": "技术要求",
        "inspectionType": "01",
        "checkTypeText": null,
        "point": "2013年3月1日起出厂的车辆，每面号牌板（架）的号牌安装孔少于2个",
        "basis": "《机动车安全技术检验项目和方法》（GB 21861-2014）第6.4.5.3条",
        "standard": "注册登记检验时，号牌及号牌安装还应满足：B）2013年3月1日起出厂的车辆，每面号牌板（架）上至少应至少设有2个号牌安装孔",
        "level": "01",
        "levelText": null,
        "dangerBasis": "",
        "isvalid": null,
        "createBy": null,
        "createDate": null,
        "updateBy": null,
        "updateDate": null
      },
      {
        "id": 62469,
        "industry": "186",
        "industryName": "科学研究和技术服务业",
        "industryitem": "186002",
        "industryitemName": null,
        "industrysubitem": "18600201",
        "industrysubitemName": null,
        "checkType": "技术要求",
        "inspectionType": "01",
        "checkTypeText": null,
        "point": "2013年3月1日起出厂的车辆，每面号牌板（架）的号牌安装孔少于2个",
        "basis": "《机动车安全技术检验项目和方法》（GB 21861-2014）第6.4.5.3条",
        "standard": "注册登记检验时，号牌及号牌安装还应满足：B）2013年3月1日起出厂的车辆，每面号牌板（架）上至少应至少设有2个号牌安装孔",
        "level": "01",
        "levelText": null,
        "dangerBasis": "",
        "isvalid": null,
        "createBy": null,
        "createDate": null,
        "updateBy": null,
        "updateDate": null
      }
    ]
  },
  "public": {
    "total": 386,
    "rows": [
      {
        "id": 20935,
        "code": "",
        "enterpriseId": 80,
        "inspectionType": "03",
        "status": 1,
        "checkTypeText": "方法与工艺",
        "point": "不达标的送检机动车，机动车安全技术检验机构未告知送检人整改，未在符合要求后再进行安全技术检验",
        "basis": "《机动车安全技术检验项目和方法》（GB 21861-2014）第5.1.2.1条",
        "standard": "送检机动车应清洁，无明显漏油、漏水、漏气现象，轮胎完好，轮胎气压正常且胎冠花纹中无异物，发动机应运转平稳，怠速稳定，无异响；装有车载诊断系统（OBD）的车辆，不应有与防抱死制动系统（ABS）、电动助力转向系统（EPS）及其他与行车安全相关的故障信息对达不到以上基本要求的送检机动车，机动车安全技术检验机构应告知送检人整改，符合要求后再进行安全技术检验",
        "level": "01",
        "dangerBasis": "",
        "checkType": null,
        "createBy": 172,
        "createDate": 1692755529000,
        "updateBy": 172,
        "updateDate": 1692755529000,
        "levelName": null,
        "levelText": null,
        "inspectionSite": null,
        "inspectionCount": null
      },
      {
        "id": 20933,
        "code": "",
        "enterpriseId": 80,
        "inspectionType": "03",
        "status": 1,
        "checkTypeText": "方法与工艺",
        "point": "不达标的送检机动车，机动车安全技术检验机构未告知送检人整改，未在符合要求后再进行安全技术检验",
        "basis": "《机动车安全技术检验项目和方法》（GB 21861-2014）第5.1.2.1条",
        "standard": "送检机动车应清洁，无明显漏油、漏水、漏气现象，轮胎完好，轮胎气压正常且胎冠花纹中无异物，发动机应运转平稳，怠速稳定，无异响；装有车载诊断系统（OBD）的车辆，不应有与防抱死制动系统（ABS）、电动助力转向系统（EPS）及其他与行车安全相关的故障信息对达不到以上基本要求的送检机动车，机动车安全技术检验机构应告知送检人整改，符合要求后再进行安全技术检验",
        "level": "01",
        "dangerBasis": "",
        "checkType": null,
        "createBy": 172,
        "createDate": 1691895672000,
        "updateBy": 172,
        "updateDate": 1691895672000,
        "levelName": null,
        "levelText": null,
        "inspectionSite": null,
        "inspectionCount": null
      },
      {
        "id": 20932,
        "code": "",
        "enterpriseId": 80,
        "inspectionType": "03",
        "status": 1,
        "checkTypeText": "方法与工艺",
        "point": "不达标的送检机动车，机动车安全技术检验机构未告知送检人整改，未在符合要求后再进行安全技术检验",
        "basis": "《机动车安全技术检验项目和方法》（GB 21861-2014）第5.1.2.1条",
        "standard": "送检机动车应清洁，无明显漏油、漏水、漏气现象，轮胎完好，轮胎气压正常且胎冠花纹中无异物，发动机应运转平稳，怠速稳定，无异响；装有车载诊断系统（OBD）的车辆，不应有与防抱死制动系统（ABS）、电动助力转向系统（EPS）及其他与行车安全相关的故障信息对达不到以上基本要求的送检机动车，机动车安全技术检验机构应告知送检人整改，符合要求后再进行安全技术检验",
        "level": "01",
        "dangerBasis": "",
        "checkType": null,
        "createBy": 25025,
        "createDate": 1691824913000,
        "updateBy": 25025,
        "updateDate": 1691824913000,
        "levelName": null,
        "levelText": null,
        "inspectionSite": null,
        "inspectionCount": null
      },
      {
        "id": 20924,
        "code": "",
        "enterpriseId": 80,
        "inspectionType": "01",
        "status": 1,
        "checkTypeText": "设备与设施",
        "point": "含粉尘的排风管道未采用法兰连接的圆形管道敷设",
        "basis": "《家具制造业防尘防毒技术规范》（AQ 4211-2010）第7.6条",
        "standard": "含粉尘的排风管道应采用法兰连接的圆形管道敷设",
        "level": "01",
        "dangerBasis": "",
        "checkType": null,
        "createBy": 18377,
        "createDate": 1689298312000,
        "updateBy": 18377,
        "updateDate": 1689298312000,
        "levelName": null,
        "levelText": null,
        "inspectionSite": null,
        "inspectionCount": null
      },
      {
        "id": 20921,
        "code": "",
        "enterpriseId": 80,
        "inspectionType": "01",
        "status": 1,
        "checkTypeText": "设备与设施",
        "point": "含粉尘的排风管道未采用法兰连接的圆形管道敷设",
        "basis": "《家具制造业防尘防毒技术规范》（AQ 4211-2010）第7.6条",
        "standard": "含粉尘的排风管道应采用法兰连接的圆形管道敷设",
        "level": "01",
        "dangerBasis": "",
        "checkType": null,
        "createBy": 172,
        "createDate": 1687248318000,
        "updateBy": 172,
        "updateDate": 1687248318000,
        "levelName": null,
        "levelText": null,
        "inspectionSite": null,
        "inspectionCount": null
      },
      {
        "id": 20920,
        "code": "",
        "enterpriseId": 80,
        "inspectionType": "01",
        "status": 1,
        "checkTypeText": "设备与设施",
        "point": "含粉尘的排风管道未采用法兰连接的圆形管道敷设",
        "basis": "《家具制造业防尘防毒技术规范》（AQ 4211-2010）第7.6条",
        "standard": "含粉尘的排风管道应采用法兰连接的圆形管道敷设",
        "level": "01",
        "dangerBasis": "",
        "checkType": null,
        "createBy": 172,
        "createDate": 1687242424000,
        "updateBy": 172,
        "updateDate": 1687242424000,
        "levelName": null,
        "levelText": null,
        "inspectionSite": null,
        "inspectionCount": null
      },
      {
        "id": 20919,
        "code": "",
        "enterpriseId": 80,
        "inspectionType": "01",
        "status": 1,
        "checkTypeText": "设备与设施",
        "point": "含粉尘的排风管道未采用法兰连接的圆形管道敷设",
        "basis": "《家具制造业防尘防毒技术规范》（AQ 4211-2010）第7.6条",
        "standard": "含粉尘的排风管道应采用法兰连接的圆形管道敷设",
        "level": "01",
        "dangerBasis": "",
        "checkType": null,
        "createBy": 172,
        "createDate": 1686657656000,
        "updateBy": 172,
        "updateDate": 1686657656000,
        "levelName": null,
        "levelText": null,
        "inspectionSite": null,
        "inspectionCount": null
      },
      {
        "id": 20916,
        "code": "",
        "enterpriseId": 80,
        "inspectionType": "01",
        "status": 1,
        "checkTypeText": "设备与设施",
        "point": "粉尘污染危害严重的设施未远离非污染设施",
        "basis": "《人造板工业生产性粉尘控制技术规程》（LY/T 1659-2006）第4.1.1.1条",
        "standard": "厂区总平面布置，在满足主体工程需要的前提下，应将粉尘污染危害严重的设施远离非污染设施，产生粉尘的车间与产生毒物的车间分开",
        "level": "01",
        "dangerBasis": null,
        "checkType": null,
        "createBy": 30958,
        "createDate": 1685680354000,
        "updateBy": 30958,
        "updateDate": 1685680354000,
        "levelName": null,
        "levelText": null,
        "inspectionSite": null,
        "inspectionCount": null
      },
      {
        "id": 20915,
        "code": "",
        "enterpriseId": 80,
        "inspectionType": "01",
        "status": 1,
        "checkTypeText": "设备与设施",
        "point": "含粉尘的排风管道未采用法兰连接的圆形管道敷设",
        "basis": "《家具制造业防尘防毒技术规范》（AQ 4211-2010）第7.6条",
        "standard": "含粉尘的排风管道应采用法兰连接的圆形管道敷设",
        "level": "01",
        "dangerBasis": "",
        "checkType": null,
        "createBy": 30958,
        "createDate": 1685680352000,
        "updateBy": 30958,
        "updateDate": 1685680352000,
        "levelName": null,
        "levelText": null,
        "inspectionSite": null,
        "inspectionCount": null
      },
      {
        "id": 20910,
        "code": "",
        "enterpriseId": 87,
        "inspectionType": "05",
        "status": 1,
        "checkTypeText": "人力与管理",
        "point": "检查除尘器布袋或更换布袋时，没有专人监护，未系好安全带",
        "basis": "《铝电解安全生产规范》（GB29741-2013）第4.2.2.3 条",
        "standard": "检查除尘器布袋或更换布袋时，应有人监护，应系好安全带，谨防从高空坠落",
        "level": "01",
        "dangerBasis": "",
        "checkType": null,
        "createBy": 30661,
        "createDate": 1683947395000,
        "updateBy": 30661,
        "updateDate": 1683947395000,
        "levelName": null,
        "levelText": null,
        "inspectionSite": null,
        "inspectionCount": null
      }
    ]
  }
}
